array_api_stubs/__init__.py
array_api_stubs/_2021_12/__init__.py
array_api_stubs/_2021_12/_types.py
array_api_stubs/_2021_12/array_object.py
array_api_stubs/_2021_12/constants.py
array_api_stubs/_2021_12/creation_functions.py
array_api_stubs/_2021_12/data_type_functions.py
array_api_stubs/_2021_12/data_types.py
array_api_stubs/_2021_12/elementwise_functions.py
array_api_stubs/_2021_12/linalg.py
array_api_stubs/_2021_12/linear_algebra_functions.py
array_api_stubs/_2021_12/manipulation_functions.py
array_api_stubs/_2021_12/searching_functions.py
array_api_stubs/_2021_12/set_functions.py
array_api_stubs/_2021_12/sorting_functions.py
array_api_stubs/_2021_12/statistical_functions.py
array_api_stubs/_2021_12/utility_functions.py
array_api_stubs/_draft/__init__.py
array_api_stubs/_draft/_types.py
array_api_stubs/_draft/array_object.py
array_api_stubs/_draft/constants.py
array_api_stubs/_draft/creation_functions.py
array_api_stubs/_draft/data_type_functions.py
array_api_stubs/_draft/data_types.py
array_api_stubs/_draft/elementwise_functions.py
array_api_stubs/_draft/fft.py
array_api_stubs/_draft/linalg.py
array_api_stubs/_draft/linear_algebra_functions.py
array_api_stubs/_draft/manipulation_functions.py
array_api_stubs/_draft/searching_functions.py
array_api_stubs/_draft/set_functions.py
array_api_stubs/_draft/sorting_functions.py
array_api_stubs/_draft/statistical_functions.py
array_api_stubs/_draft/utility_functions.py
array_api_stubs-0.0.2.dist-info/LICENSE
array_api_stubs-0.0.2.dist-info/METADATA
array_api_stubs-0.0.2.dist-info/WHEEL
array_api_stubs-0.0.2.dist-info/top_level.txt
array_api_stubs-0.0.2.dist-info/RECORD
