Metadata-Version: 2.1
Name: array-api-stubs
Version: 0.0.2
Summary: Stubs for the array API standard
License: MIT License        
Project-URL: Source, https://github.com/data-apis/array-api/
Project-URL: Documentation, https://data-apis.org/array-api/
Project-URL: Homepage, https://data-apis.org/
Requires-Python: >=3.8
License-File: LICENSE
Provides-Extra: doc
Requires-Dist: sphinx (==4.3.0) ; extra == 'doc'
Requires-Dist: sphinx-material (==0.0.30) ; extra == 'doc'
Requires-Dist: myst-parser ; extra == 'doc'
Requires-Dist: sphinx-markdown-tables ; extra == 'doc'
Requires-Dist: sphinx-copybutton ; extra == 'doc'
Requires-Dist: docutils (<0.18) ; extra == 'doc'
Requires-Dist: sphinx-math-dollar ; extra == 'doc'
